[
    {
        "id": "quiz-kg-1",
        "title": {
            "ar": "اختبار الأشكال والألوان",
            "en": "Shapes and Colors Quiz"
        },
        "subject": {
            "ar": "رياضيات",
            "en": "Mathematics"
        },
        "grade": "KG",
        "date": "2026-02-05",
        "duration": 15,
        "totalPoints": 6,
        "questions": [
            {
                "id": "q1",
                "question": {
                    "ar": "كم عدد الدوائر؟",
                    "en": "How many circles?"
                },
                "options": [
                    {
                        "ar": "2",
                        "en": "2"
                    },
                    {
                        "ar": "3",
                        "en": "3"
                    },
                    {
                        "ar": "4",
                        "en": "4"
                    },
                    {
                        "ar": "5",
                        "en": "5"
                    }
                ],
                "correctAnswer": 1,
                "points": 2
            }
        ]
    },
    {
        "id": "quiz-kg-2",
        "title": {
            "ar": "اختبار الحروف",
            "en": "Letters Quiz"
        },
        "subject": {
            "ar": "لغة عربية",
            "en": "Arabic Language"
        },
        "grade": "KG",
        "date": "2026-02-07",
        "duration": 15,
        "totalPoints": 6,
        "questions": [
            {
                "id": "q1",
                "question": {
                    "ar": "ما هو الحرف الأول في كلمة 'أسد'؟",
                    "en": "What is the first letter in the word 'أسد'?"
                },
                "options": [
                    {
                        "ar": "أ",
                        "en": "أ"
                    },
                    {
                        "ar": "ب",
                        "en": "ب"
                    },
                    {
                        "ar": "س",
                        "en": "س"
                    },
                    {
                        "ar": "د",
                        "en": "د"
                    }
                ],
                "correctAnswer": 0,
                "points": 2
            }
        ]
    },
    {
        "id": "quiz-1-1",
        "title": {
            "ar": "اختبار الجمع البسيط",
            "en": "Simple Addition Quiz"
        },
        "subject": {
            "ar": "رياضيات",
            "en": "Mathematics"
        },
        "grade": "1",
        "date": "2026-02-10",
        "duration": 20,
        "totalPoints": 8,
        "questions": [
            {
                "id": "q1",
                "question": {
                    "ar": "كم يساوي 3 + 2؟",
                    "en": "What is 3 + 2?"
                },
                "options": [
                    {
                        "ar": "4",
                        "en": "4"
                    },
                    {
                        "ar": "5",
                        "en": "5"
                    },
                    {
                        "ar": "6",
                        "en": "6"
                    },
                    {
                        "ar": "7",
                        "en": "7"
                    }
                ],
                "correctAnswer": 1,
                "points": 2
            }
        ]
    },
    {
        "id": "quiz-1-2",
        "title": {
            "ar": "اختبار القراءة",
            "en": "Reading Quiz"
        },
        "subject": {
            "ar": "لغة عربية",
            "en": "Arabic Language"
        },
        "grade": "1",
        "date": "2026-02-12",
        "duration": 20,
        "totalPoints": 8,
        "questions": [
            {
                "id": "q1",
                "question": {
                    "ar": "كم كلمة في الجملة: 'القطة تلعب'؟",
                    "en": "How many words in the sentence: 'القطة تلعب'?"
                },
                "options": [
                    {
                        "ar": "1",
                        "en": "1"
                    },
                    {
                        "ar": "2",
                        "en": "2"
                    },
                    {
                        "ar": "3",
                        "en": "3"
                    },
                    {
                        "ar": "4",
                        "en": "4"
                    }
                ],
                "correctAnswer": 1,
                "points": 2
            }
        ]
    },
    {
        "id": "quiz-2-1",
        "title": {
            "ar": "اختبار الجمع والطرح",
            "en": "Addition and Subtraction Quiz"
        },
        "subject": {
            "ar": "رياضيات",
            "en": "Mathematics"
        },
        "grade": "2",
        "date": "2026-01-24",
        "duration": 20,
        "totalPoints": 8,
        "questions": [
            {
                "id": "q1",
                "question": {
                    "ar": "كم يساوي 15 + 7؟",
                    "en": "What is 15 + 7?"
                },
                "options": [
                    {
                        "ar": "20",
                        "en": "20"
                    },
                    {
                        "ar": "21",
                        "en": "21"
                    },
                    {
                        "ar": "22",
                        "en": "22"
                    },
                    {
                        "ar": "23",
                        "en": "23"
                    }
                ],
                "correctAnswer": 2,
                "points": 2
            }
        ]
    },
    {
        "id": "quiz-2-2",
        "title": {
            "ar": "اختبار الكلمات والجمل",
            "en": "Words and Sentences Quiz"
        },
        "subject": {
            "ar": "لغة عربية",
            "en": "Arabic Language"
        },
        "grade": "2",
        "date": "2026-01-26",
        "duration": 20,
        "totalPoints": 8,
        "questions": [
            {
                "id": "q1",
                "question": {
                    "ar": "ما هو عكس كلمة 'كبير'؟",
                    "en": "What is the opposite of 'big'?"
                },
                "options": [
                    {
                        "ar": "صغير",
                        "en": "small"
                    },
                    {
                        "ar": "طويل",
                        "en": "tall"
                    },
                    {
                        "ar": "واسع",
                        "en": "wide"
                    },
                    {
                        "ar": "قصير",
                        "en": "short"
                    }
                ],
                "correctAnswer": 0,
                "points": 2
            }
        ]
    },
    {
        "id": "quiz-3-1",
        "title": {
            "ar": "اختبار الضرب",
            "en": "Multiplication Quiz"
        },
        "subject": {
            "ar": "رياضيات",
            "en": "Mathematics"
        },
        "grade": "3",
        "date": "2026-01-28",
        "duration": 25,
        "totalPoints": 10,
        "questions": [
            {
                "id": "q1",
                "question": {
                    "ar": "كم يساوي 5 × 4؟",
                    "en": "What is 5 × 4?"
                },
                "options": [
                    {
                        "ar": "15",
                        "en": "15"
                    },
                    {
                        "ar": "20",
                        "en": "20"
                    },
                    {
                        "ar": "25",
                        "en": "25"
                    },
                    {
                        "ar": "30",
                        "en": "30"
                    }
                ],
                "correctAnswer": 1,
                "points": 2
            }
        ]
    },
    {
        "id": "quiz-3-2",
        "title": {
            "ar": "اختبار العلوم - النباتات",
            "en": "Science Quiz - Plants"
        },
        "subject": {
            "ar": "علوم",
            "en": "Science"
        },
        "grade": "3",
        "date": "2026-01-30",
        "duration": 25,
        "totalPoints": 10,
        "questions": [
            {
                "id": "q1",
                "question": {
                    "ar": "ما الذي تحتاجه النباتات للنمو؟",
                    "en": "What do plants need to grow?"
                },
                "options": [
                    {
                        "ar": "ماء وضوء",
                        "en": "Water and light"
                    },
                    {
                        "ar": "سكر فقط",
                        "en": "Only sugar"
                    },
                    {
                        "ar": "ملح فقط",
                        "en": "Only salt"
                    },
                    {
                        "ar": "هواء فقط",
                        "en": "Only air"
                    }
                ],
                "correctAnswer": 0,
                "points": 2
            }
        ]
    },
    {
        "id": "quiz-4-1",
        "title": {
            "ar": "اختبار القسمة",
            "en": "Division Quiz"
        },
        "subject": {
            "ar": "رياضيات",
            "en": "Mathematics"
        },
        "grade": "4",
        "date": "2026-02-01",
        "duration": 25,
        "totalPoints": 10,
        "questions": [
            {
                "id": "q1",
                "question": {
                    "ar": "كم يساوي 20 ÷ 5؟",
                    "en": "What is 20 ÷ 5?"
                },
                "options": [
                    {
                        "ar": "3",
                        "en": "3"
                    },
                    {
                        "ar": "4",
                        "en": "4"
                    },
                    {
                        "ar": "5",
                        "en": "5"
                    },
                    {
                        "ar": "6",
                        "en": "6"
                    }
                ],
                "correctAnswer": 1,
                "points": 2
            }
        ]
    },
    {
        "id": "quiz-4-2",
        "title": {
            "ar": "اختبار الإنجليزي - الحيوانات",
            "en": "English Quiz - Animals"
        },
        "subject": {
            "ar": "لغة إنجليزية",
            "en": "English Language"
        },
        "grade": "4",
        "date": "2026-02-03",
        "duration": 25,
        "totalPoints": 10,
        "questions": [
            {
                "id": "q1",
                "question": {
                    "ar": "ما هو الحيوان الأكبر في البحر؟",
                    "en": "What is the largest animal in the sea?"
                },
                "options": [
                    {
                        "ar": "الحوت الأزرق",
                        "en": "Blue Whale"
                    },
                    {
                        "ar": "القرش",
                        "en": "Shark"
                    },
                    {
                        "ar": "الدولفين",
                        "en": "Dolphin"
                    },
                    {
                        "ar": "السلحفاة",
                        "en": "Turtle"
                    }
                ],
                "correctAnswer": 0,
                "points": 2
            }
        ]
    },
    {
        "id": "quiz-5-1",
        "title": {
            "ar": "اختبار الكسور",
            "en": "Fractions Quiz"
        },
        "subject": {
            "ar": "رياضيات",
            "en": "Mathematics"
        },
        "grade": "5",
        "date": "2026-02-05",
        "duration": 30,
        "totalPoints": 10,
        "questions": [
            {
                "id": "q1",
                "question": {
                    "ar": "كم يساوي ½ + ¼؟",
                    "en": "What is ½ + ¼?"
                },
                "options": [
                    {
                        "ar": "¼",
                        "en": "¼"
                    },
                    {
                        "ar": "½",
                        "en": "½"
                    },
                    {
                        "ar": "¾",
                        "en": "¾"
                    },
                    {
                        "ar": "1",
                        "en": "1"
                    }
                ],
                "correctAnswer": 2,
                "points": 2
            }
        ]
    },
    {
        "id": "quiz-5-2",
        "title": {
            "ar": "اختبار التاريخ - الحضارات",
            "en": "History Quiz - Civilizations"
        },
        "subject": {
            "ar": "تاريخ",
            "en": "History"
        },
        "grade": "5",
        "date": "2026-02-07",
        "duration": 30,
        "totalPoints": 10,
        "questions": [
            {
                "id": "q1",
                "question": {
                    "ar": "أين نشأت الحضارة الفرعونية؟",
                    "en": "Where did the Pharaonic civilization originate?"
                },
                "options": [
                    {
                        "ar": "مصر",
                        "en": "Egypt"
                    },
                    {
                        "ar": "العراق",
                        "en": "Iraq"
                    },
                    {
                        "ar": "سوريا",
                        "en": "Syria"
                    },
                    {
                        "ar": "اليونان",
                        "en": "Greece"
                    }
                ],
                "correctAnswer": 0,
                "points": 2
            }
        ]
    },
    {
        "id": "quiz-6-1",
        "title": {
            "ar": "اختبار الهندسة - المساحات",
            "en": "Geometry Quiz - Areas"
        },
        "subject": {
            "ar": "رياضيات",
            "en": "Mathematics"
        },
        "grade": "6",
        "date": "2026-02-08",
        "duration": 30,
        "totalPoints": 10,
        "questions": [
            {
                "id": "q1",
                "question": {
                    "ar": "ما هي مساحة المستطيل الذي طوله 5 وعرضه 3؟",
                    "en": "What is the area of a rectangle with length 5 and width 3?"
                },
                "options": [
                    {
                        "ar": "8",
                        "en": "8"
                    },
                    {
                        "ar": "15",
                        "en": "15"
                    },
                    {
                        "ar": "16",
                        "en": "16"
                    },
                    {
                        "ar": "20",
                        "en": "20"
                    }
                ],
                "correctAnswer": 1,
                "points": 2
            }
        ]
    },
    {
        "id": "quiz-6-2",
        "title": {
            "ar": "اختبار الجغرافيا - القارات",
            "en": "Geography Quiz - Continents"
        },
        "subject": {
            "ar": "جغرافيا",
            "en": "Geography"
        },
        "grade": "6",
        "date": "2026-02-10",
        "duration": 30,
        "totalPoints": 10,
        "questions": [
            {
                "id": "q1",
                "question": {
                    "ar": "كم عدد القارات في العالم؟",
                    "en": "How many continents are in the world?"
                },
                "options": [
                    {
                        "ar": "5",
                        "en": "5"
                    },
                    {
                        "ar": "6",
                        "en": "6"
                    },
                    {
                        "ar": "7",
                        "en": "7"
                    },
                    {
                        "ar": "8",
                        "en": "8"
                    }
                ],
                "correctAnswer": 2,
                "points": 2
            }
        ]
    }
]